{
    "os": "Windows-10-10.0.22000-SP0",
    "python": "3.10.6",
    "heartbeatAt": "2022-10-22T17:32:05.390020",
    "startedAt": "2022-10-22T17:32:04.632632",
    "docker": null,
    "gpu": "NVIDIA GeForce RTX 3070 Laptop GPU",
    "gpu_count": 1,
    "cpu_count": 16,
    "cuda": null,
    "args": [],
    "state": "running",
    "program": "C:\\GitHub\\Signal-Space-GAN\\eeggan\\train\\run_2.py",
    "codePath": "eeggan\\train\\run_2.py",
    "git": {
        "remote": "https://github.com/AdamSobieszek/Signal-Space-GAN.git",
        "commit": "025d34742e3be555c3fb99b57ffbfa2da673ed53"
    },
    "email": "hplisiecki@gmail.com",
    "root": "C:/GitHub/Signal-Space-GAN",
    "host": "MSI",
    "username": "hplis",
    "executable": "C:\\Users\\hplis\\.conda\\envs\\Signal-Space-GAN\\python.exe"
}
